{
  "error": "",
  "response": {
    "id": 24,
    "name": "FE_Credit_Province",
    "columns": [
      "Province"
    ],
    "values": [
      {
        "id": 9605,
        "values": [
          "Tỉnh An Giang"
        ]
      },
      {
        "id": 9604,
        "values": [
          "Tỉnh Bắc Giang"
        ]
      },
      {
        "id": 9603,
        "values": [
          "Tỉnh Bắc Kạn"
        ]
      },
      {
        "id": 9602,
        "values": [
          "Tỉnh Bạc Liêu"
        ]
      },
      {
        "id": 9601,
        "values": [
          "Tỉnh Bắc Ninh"
        ]
      },
      {
        "id": 9600,
        "values": [
          "Tỉnh Bến Tre"
        ]
      },
      {
        "id": 9599,
        "values": [
          "Tỉnh Bà Rịa - Vũng Tàu"
        ]
      },
      {
        "id": 9598,
        "values": [
          "Tỉnh Bình Dương"
        ]
      },
      {
        "id": 9597,
        "values": [
          "Tỉnh Bình Phước"
        ]
      },
      {
        "id": 9596,
        "values": [
          "Tỉnh Bình Thuận"
        ]
      },
      {
        "id": 9595,
        "values": [
          "Tỉnh Bình Định"
        ]
      },
      {
        "id": 9594,
        "values": [
          "Tỉnh Cao Bằng"
        ]
      },
      {
        "id": 9593,
        "values": [
          "Tỉnh Cà Mau"
        ]
      },
      {
        "id": 9592,
        "values": [
          "Tỉnh Gia Lai"
        ]
      },
      {
        "id": 9591,
        "values": [
          "Tỉnh Hải Dương"
        ]
      },
      {
        "id": 9590,
        "values": [
          "Tỉnh Hậu Giang"
        ]
      },
      {
        "id": 9589,
        "values": [
          "Tỉnh Hòa Bình"
        ]
      },
      {
        "id": 9588,
        "values": [
          "Tỉnh Hưng Yên"
        ]
      },
      {
        "id": 9587,
        "values": [
          "Tỉnh Hà Giang"
        ]
      },
      {
        "id": 9586,
        "values": [
          "Tỉnh Hà Nam"
        ]
      },
      {
        "id": 9585,
        "values": [
          "Tỉnh Hà Tĩnh"
        ]
      },
      {
        "id": 9584,
        "values": [
          "Tỉnh Khánh Hòa"
        ]
      },
      {
        "id": 9583,
        "values": [
          "Tỉnh Kiên Giang"
        ]
      },
      {
        "id": 9582,
        "values": [
          "Tỉnh Kon Tum"
        ]
      },
      {
        "id": 9581,
        "values": [
          "Tỉnh Lạng Sơn"
        ]
      },
      {
        "id": 9580,
        "values": [
          "Tỉnh Lai Châu"
        ]
      },
      {
        "id": 9579,
        "values": [
          "Tỉnh Long An"
        ]
      },
      {
        "id": 9578,
        "values": [
          "Tỉnh Lào Cai"
        ]
      },
      {
        "id": 9577,
        "values": [
          "Tỉnh Lâm Đồng"
        ]
      },
      {
        "id": 9576,
        "values": [
          "Tỉnh Nam Định"
        ]
      },
      {
        "id": 9575,
        "values": [
          "Tỉnh Nghệ An"
        ]
      },
      {
        "id": 9574,
        "values": [
          "Tỉnh Ninh Bình"
        ]
      },
      {
        "id": 9573,
        "values": [
          "Tỉnh Ninh Thuận"
        ]
      },
      {
        "id": 9572,
        "values": [
          "Tỉnh Phú Thọ"
        ]
      },
      {
        "id": 9571,
        "values": [
          "Tỉnh Phú Yên"
        ]
      },
      {
        "id": 9570,
        "values": [
          "Tỉnh Quảng Bình"
        ]
      },
      {
        "id": 9569,
        "values": [
          "Tỉnh Quảng Nam"
        ]
      },
      {
        "id": 9568,
        "values": [
          "Tỉnh Quảng Ngãi"
        ]
      },
      {
        "id": 9567,
        "values": [
          "Tỉnh Quảng Ninh"
        ]
      },
      {
        "id": 9566,
        "values": [
          "Tỉnh Quảng Trị"
        ]
      },
      {
        "id": 9565,
        "values": [
          "Tỉnh Sơn La"
        ]
      },
      {
        "id": 9564,
        "values": [
          "Tỉnh Sóc Trăng"
        ]
      },
      {
        "id": 9563,
        "values": [
          "Tỉnh Thừa Thiên - Huế"
        ]
      },
      {
        "id": 9562,
        "values": [
          "Tỉnh Thanh Hóa"
        ]
      },
      {
        "id": 9561,
        "values": [
          "Tỉnh Thái Bình"
        ]
      },
      {
        "id": 9560,
        "values": [
          "Tỉnh Thái Nguyên"
        ]
      },
      {
        "id": 9559,
        "values": [
          "Tỉnh Tiền Giang"
        ]
      },
      {
        "id": 9558,
        "values": [
          "Tỉnh Trà Vinh"
        ]
      },
      {
        "id": 9557,
        "values": [
          "Tỉnh Tuyên Quang"
        ]
      },
      {
        "id": 9556,
        "values": [
          "Tỉnh Tây Ninh"
        ]
      },
      {
        "id": 9555,
        "values": [
          "Tỉnh Vĩnh Long"
        ]
      },
      {
        "id": 9554,
        "values": [
          "Tỉnh Vĩnh Phúc"
        ]
      },
      {
        "id": 9553,
        "values": [
          "Tỉnh Yên Bái"
        ]
      },
      {
        "id": 9552,
        "values": [
          "Tỉnh Đồng Nai"
        ]
      },
      {
        "id": 9551,
        "values": [
          "Tỉnh Đồng Tháp"
        ]
      },
      {
        "id": 9550,
        "values": [
          "Tỉnh Đắk Lắk"
        ]
      },
      {
        "id": 9549,
        "values": [
          "Tỉnh Đắk Nông"
        ]
      },
      {
        "id": 9548,
        "values": [
          "Tỉnh Điện Biên"
        ]
      },
      {
        "id": 9547,
        "values": [
          "Thành phố Cần Thơ"
        ]
      },
      {
        "id": 9546,
        "values": [
          "Thành phố Hải Phòng"
        ]
      },
      {
        "id": 9545,
        "values": [
          "Thành phố Hà Nội"
        ]
      },
      {
        "id": 9544,
        "values": [
          "Thành phố Đà Nẵng"
        ]
      },
      {
        "id": 9543,
        "values": [
          "TP Hồ Chí Minh"
        ]
      },
      {
        "id": 9542,
        "values": [
          "CUC CSDKQL CU TRU VA DLQG VE DAN CU"
        ]
      }
    ]
  }
}